pavlovadm/__init__.py
pavlovadm/__main__.py
pavlovadm/__pkginfo__.py
pavlovadm/colortext.py
pavlovadm/pavlovadm.py
pavlovadm/example/BalancingTable.csv
pavlovadm/example/Game.ini
pavlovadm/example/pavlovadm.conf
pavlovadm/example/public.ini
pavlovadm-2.0.data/data/share/pavlovadm/BalancingTable.csv
pavlovadm-2.0.data/data/share/pavlovadm/Game.ini
pavlovadm-2.0.data/data/share/pavlovadm/pavlovadm.conf
pavlovadm-2.0.data/data/share/pavlovadm/public.ini
pavlovadm-2.0.dist-info/METADATA
pavlovadm-2.0.dist-info/WHEEL
pavlovadm-2.0.dist-info/entry_points.txt
pavlovadm-2.0.dist-info/top_level.txt
pavlovadm-2.0.dist-info/RECORD
